{
  "note_id": "auto_20260404_0949",
  "note_title": "The Cost of Survival",
  "output_dir": "output/20260404_0951_the_cost_of_survival",
  "slide_files": [
    "output/20260404_0951_the_cost_of_survival/slide_01.jpg",
    "output/20260404_0951_the_cost_of_survival/slide_02.jpg",
    "output/20260404_0951_the_cost_of_survival/slide_03.jpg",
    "output/20260404_0951_the_cost_of_survival/slide_04.jpg",
    "output/20260404_0951_the_cost_of_survival/slide_05.jpg",
    "output/20260404_0951_the_cost_of_survival/slide_06.jpg",
    "output/20260404_0951_the_cost_of_survival/slide_07.jpg"
  ],
  "caption": "Your nervous system made a decision before you had language.\n\nIt chose the known over the felt.\nThe managed over the alive.\nThe controlled over the true.\n\nAnd it worked. You survived.\n\nBut somewhere along the way, the thing that saved you became the thing that sealed you in.\n\nRegulation without presence is just a higher-functioning freeze.\nComfort without depth is just numbness with better furniture.\n\nThe work is not to override the pattern.\nIt is to finally show your body that the emergency is over.\n\nThat it is allowed to choose something other than safe.\nThat life was always on the other side of the wall it built.\n\n.\n.\n.\n#nervoussystem #somatichealing #consciousness #survivalmode #nervousystemregulation #traumarecovery #embodiment #awakenedliving #reprogramming #innerwork",
  "generated_at": "2026-04-04T09:51:05.516208",
  "dry_run": false
}